rangelist/__init__.py
rangelist/point.py
rangelist/rangeitem.py
rangelist/rangelist.py
rangelist-0.0.4.dist-info/LICENSE
rangelist-0.0.4.dist-info/METADATA
rangelist-0.0.4.dist-info/WHEEL
rangelist-0.0.4.dist-info/top_level.txt
rangelist-0.0.4.dist-info/RECORD
