Metadata-Version: 2.1
Name: rangelist
Version: 0.0.4
Summary: List of intersecting ranges
Home-page: https://github.com/alexeidjango/rangelist
Author: Alexei M
Author-email: alexeidjango@gmail.com
License: UNKNOWN
Platform: UNKNOWN
Classifier: Programming Language :: Python
Classifier: Development Status :: 4 - Beta
Classifier: License :: OSI Approved :: MIT License
Classifier: Operating System :: OS Independent
Requires-Python: >=2.7
